Workbook

Sheet MiniGrid
A1: Indicators | B1: Current Quarter | C1: To-date
A2: Minimum Subsidy Tender for Mini Grids
A3: Isolated Mini Grid
A4: Benefiting Communities | B4: 34 | D4: Benefiting Communities
A5: Isolated Mini Grid Approved | D5: Isolated Mini Grid Approved
A6: Isolated Mini Grid Commissioned | D6: Isolated Mini Grid Commissioned
A7: Isolated Mini-Grid Ongoing | D7: Isolated Mini-Grid Ongoing
A8: Population of Beneficiaries | D8: Population of Beneficiaries
A9: Population of Female Beneficiaries | D9: Population of Female Beneficiaries
A10: Population of Household Beneficiary | D10: Population of Household Beneficiary
A11: Population of Female Headed Household Beneficiaries | D11: Population of Female Headed Household Beneficiaries
A12: Population of MSME Beneficiaries | D12: Population of MSME Beneficiaries
A13: Population of Female Managed MSME Beneficiaries | D13: Population of Female Managed MSME Beneficiaries
A14: Population of New MSMEs enabled | D14: Population of New MSMEs enabled
A15: Population of Public Institution Beneficiaries | D15: Population of Public Institutition Beneficiaries
A16: Mini-Grid installed energy capacity | D16: Mini-Grid installed energy capacity
... A19: Average outage events per month | D19: Average outage events per month
A20: Grant Disbursed
A21: Private Sector Fund Mobilised
A22: Gasoline generator sets replaced | B22: 344
A24: Interconnected Mini Grid | D24: Gasoline generator sets replaced
A25: Benefiting Communities | B25: 35
A26: Interconnected Mini Grid Approved
A27: Isolated Mini Grid Commissioned
A28: Interconnected Mini-Grid Ongoing
A29: Population of Households connected
A30: Population of Female Households connected
A31: Population of PUE and Economic Users connected
A32: Population of Female Headed Household beneficiaries
A33: Population of MSME beneficiaries
A34: Population of Female Managed MSME beneficiaries
A35: Population of New MSMEs enabled
A36: Population of Public Institution beneficiary
A37: Mini-Grid installed energy capacity
... A42: Private Sector Fund Mobilised
A43: Gasoline generator sets replaced | B43: 36
A45: Solar Rooftop Solutions
A46: Solar Rooftop Solutions Approved | B46: 37
A47: Solar Rooftop Solutions Commissioned
A48: Population of Benefiting Health Institutions
A49: Gasoline generator sets replaced | B49: 38
A51: Performance Base Grant
A52: Isolated Mini Grid
A53: Benefiting Communities | B53: 39 | D53: Benefiting Communities
A54: Isolated Mini Grid Approved | D54: Isolated Mini Grid Approved
A55: Isolated Mini Grid Commissioned | D55: Isolated Mini Grid Commissioned
A56: Isolated Mini-Grid Ongoing | D56: Isolated Mini-Grid Ongoing
A57: Population of beneficiaries | D57: Population of beneficiaries
A58: Population of Female beneficiaries | D58: Population of Female beneficiaries
A59: Population of Households | D59: Population of Households
A60: Population of Female Headed Household beneficiaries | D60: Population of Female Headed Household beneficiaries
A61: Population of MSME beneficiaries | D61: Population of MSME beneficiaries
A62: Population of Female Managed MSME beneficiaries | D62: Population of Female Managed MSME beneficiaries
A63: Population of New MSMEs enabled | D63: Population of New MSMEs enabled
A64: Population of Public Institution beneficiary | D64: Population of Public Institution beneficiary
A65: Mini-Grid installed energy capacity | D65: Mini-Grid installed energy capacity
... A68: Average outage events per month | D68: Average outage events per month
A69: Gasoline generator sets replaced | B69: 40 | D69: Gasoline generator sets replaced
A71: Interconnected Mini Grid
A72: Benefiting Communities | B72: 40
A73: Interconnected Mini Grid Approved
A74: Isolated Mini Grid Commissioned
A75: Interconnected Mini-Grid Ongoing
A76: Population of Households connected
A77: Population of Female Households connected
A78: Population of PUE and Economic Users connected
A79: Population of Female PUE and Economic Users
A80: Population of New PUE and Economic enabled
A81: Population of Public Institution beneficiary
A82: Mini-Grid installed energy capacity
A83: Mini-Grid Energy generated
A84: Average daily hours of electricity supply
A85: Average outage events per month
A86: Gasoline generator sets replaced | B86: 44
A88: Summary and Next Steps
A89: Key Achievements | B89: Challenges | D89: Way Forward | G89: Actions Planned for Next Period

Sheet StandAlone
B1: STAND-ALONE SOLAR SYSTEMS
B3: Reporting Period______________________________________
B4: Indicators | C4: Current Quarter | D4: To-date
B5: Performance Based Grants for Standalone Solar Systems
B6: Solar Home Systems deployed | C6: 23
B7: Installed Energy Capacity
B8: Benefitting Households
B9: Benefiting Female Headed Households
B10: Benefiting MSMES
B11: Benefiting Female Owned MSMES
B12: Benefiting Agricultural Business
B13: Benefiting Female Owned Agricultural Business
B14: Gasoline generator sets replaced | C14: 24
B16: Catalytic Grants
B17: Poor/Displaced Communities Identified | C17: 25
B18: Poor/Displaced Communities Approved
B19: Solar Solution Approved
B20: Solar Solution Completed
B21: Solar Solution On-going
B22: Installed Energy Capacity
B23: Population of Households
B24: Population of Female Headed Households
B25: Population of PUE and Economic Users
B26: Population of Female PUE and Economic Users
B27: Gasoline generator sets replaced | C27: 26
B29: Summary and Next Steps
B30: Key Achievements | C30: Challenges | E30: Way Forward | H30: Actions Planned for Next Period

Sheet Sheet11
B1: PERFORMANCE INDICATORS | C1: Unit of Measure | D1: Achievement
D2: Current Quarter | E2: To-date
A3: 1 | B3: SOLAR HYBRID MINI GRIDS FOR ECONOMIC DEVELOPMENT
A4: 1.1 | B4: Minimum Subsidy Tender for Mini Grids
A5: 1.1.1 | B5: Isolated Mini Grid
A6: 1.1.1.1 | B6: Benefiting Communities | C6: No. | D6: =SUM(MiniGrid!B4) -> 34 | E6: =SUM(MiniGrid!C4) -> 0
A7: 1.1.1.2 | B7: Isolated Mini Grid Approved | C7: No. | D7: =SUM(MiniGrid!B5) -> 0 | E7: =SUM(MiniGrid!C5) -> 0
A8: 1.1.1.3 | B8: Isolated Mini Grid Commissioned | C8: No. | D8: =SUM(MiniGrid!B6) -> 0 | E8: =SUM(MiniGrid!C6) -> 0
A9: 1.1.1.4 | B9: Isolated Mini-Grid Ongoing | C9: No. | D9: =SUM(MiniGrid!B7) -> 0 | E9: =SUM(MiniGrid!C7) -> 0
A10: 1.1.1.5 | B10: Population of Beneficiaries | C10: No. | D10: =SUM(MiniGrid!B8) -> 0 | E10: =SUM(MiniGrid!C8) -> 0
A11: 1.1.1.6 | B11: Population of Female Beneficiaries | C11: No. | D11: =SUM(MiniGrid!B9) -> 0 | E11: =SUM(MiniGrid!C9) -> 0
A12: 1.1.1.7 | B12: Population of Household Beneficiary | C12: No. | D12: =SUM(MiniGrid!B10) -> 0 | E12: =SUM(MiniGrid!C10) -> 0
A13: 1.1.1.8 | B13: Population of Female Headed Household Beneficiaries | C13: No. | D13: =SUM(MiniGrid!B11) -> 0 | E13: =SUM(MiniGrid!C11) -> 0
A14: 1.1.1.9 | B14: Population of MSME Beneficiaries | C14: No. | D14: =SUM(MiniGrid!B12) -> 0 | E14: =SUM(MiniGrid!C12) -> 0
A15: 1.1.1.10 | B15: Population of Female Managed MSME Beneficiaries | C15: No. | D15: =SUM(MiniGrid!B13) -> 0 | E15: =SUM(MiniGrid!C13) -> 0
A16: 1.1.1.11 | B16: Population of New MSMEs enabled | C16: No. | D16: =SUM(MiniGrid!B14) -> 0 | E16: =SUM(MiniGrid!C14) -> 0
A17: 1.1.1.12 | B17: Population of Public Institutition Beneficiaries | C17: No. | D17: =SUM(MiniGrid!B15) -> 0 | E17: =SUM(MiniGrid!C15) -> 0
... A21: 1.1.1.16 | B21: Average outage events per month | C21: No. | D21: =SUM(MiniGrid!B19) -> 0 | E21: =SUM(MiniGrid!C19) -> 0
A22: 1.1.1.19 | B22: Private Sector Fund Mobilised | C22: Naira | D22: =SUM(MiniGrid!B21) -> 0 | E22: =SUM(MiniGrid!C23) -> 0
A23: 1.1.1.21 | B23: Gasoline generator sets replaced | C23: No. | D23: =SUM(MiniGrid!B22) -> 344 | E23: =SUM(MiniGrid!C24) -> 0
A25: 1.1.2 | B25: Interconnected Mini Grid
A26: 1.1.2.1 | B26: Benefiting Communities | C26: No. | D26: =SUM(MiniGrid!B25) -> 35 | E26: =SUM(MiniGrid!C25) -> 0
A27: 1.1.2.2 | B27: Interconnected Mini Grid Approved | C27: No. | D27: =SUM(MiniGrid!B26) -> 0 | E27: =SUM(MiniGrid!C26) -> 0
A28: 1.1.2.3 | B28: Isolated Mini Grid Commissioned | C28: No. | D28: =SUM(MiniGrid!B27) -> 0 | E28: =SUM(MiniGrid!C27) -> 0
A29: 1.1.2.4 | B29: Interconnected Mini-Grid Ongoing | C29: No. | D29: =SUM(MiniGrid!B28) -> 0 | E29: =SUM(MiniGrid!C28) -> 0
A30: 1.1.2.5 | B30: Population of Households connected | C30: No. | D30: =SUM(MiniGrid!B29) -> 0 | E30: =SUM(MiniGrid!C29) -> 0
A31: 1.1.2.6 | B31: Population of Female Households connected | C31: No. | D31: =SUM(MiniGrid!B30) -> 0 | E31: =SUM(MiniGrid!C30) -> 0
A32: 1.1.2.7 | B32: Population of PUE and Economic Users connected | C32: No. | D32: =SUM(MiniGrid!B31) -> 0 | E32: =SUM(MiniGrid!C31) -> 0
A33: 1.1.1.8 | B33: Population of Female Headed Household beneficiaries | C33: No. | D33: =SUM(MiniGrid!B32) -> 0 | E33: =SUM(MiniGrid!C32) -> 0
A34: 1.1.1.9 | B34: Population of MSME beneficiaries | C34: No. | D34: =SUM(MiniGrid!B33) -> 0 | E34: =SUM(MiniGrid!C33) -> 0
A35: 1.1.1.10 | B35: Population of Female Managed MSME beneficiaries | C35: No. | D35: =SUM(MiniGrid!B34) -> 0 | E35: =SUM(MiniGrid!C34) -> 0
A36: 1.1.1.11 | B36: Population of New MSMEs enabled | C36: No. | D36: =SUM(MiniGrid!B35) -> 0 | E36: =SUM(MiniGrid!C35) -> 0
A37: 1.1.1.12 | B37: Population of Public Institutition beneficiary | C37: KW | D37: =SUM(MiniGrid!B36) -> 0 | E37: =SUM(MiniGrid!C36) -> 0
... A41: 1.1.1.16 | B41: Average outage events per month | C41: No. | D41: =SUM(MiniGrid!B40) -> 0 | E41: =SUM(MiniGrid!C40) -> 0
A42: 1.1.1.18 | B42: Private Sector Fund Mobilised | C42: Naira | D42: =SUM(MiniGrid!B42) -> 0 | E42: =SUM(MiniGrid!C42) -> 0
A43: 1.1.1.19 | B43: Gasoline generator sets replaced | C43: No. | D43: =SUM(MiniGrid!B43) -> 36 | E43: =SUM(MiniGrid!C43) -> 0
A45: 1.1.3 | B45: Solar Rooftop Solutions
A46: 1.1.3.1 | B46: Solar Rooftop Solutions Approved | C46: No. | D46: =SUM(MiniGrid!B46) -> 37 | E46: =SUM(MiniGrid!C46) -> 0
A47: 1.1.3.2 | B47: Solar Rooftop Solutions Commissioned | C47: No. | D47: =SUM(MiniGrid!B47) -> 0 | E47: =SUM(MiniGrid!C47) -> 0
A48: 1.1.3.3 | B48: Population of Benefiting Health Institutions | C48: No. | D48: =SUM(MiniGrid!B48) -> 0 | E48: =SUM(MiniGrid!C48) -> 0
A49: 1.1.3.5 | B49: State Government Fund Mobilized | C49: Naira.
A50: 1.1.3.6 | B50: Gasoline generator sets replaced | C50: No. | D50: =SUM(MiniGrid!B49) -> 38 | E50: =SUM(MiniGrid!C49) -> 0
A52: 1.2 | B52: Performance Base Grant
A53: 1.2.1 | B53: Isolated Mini Grid
A54: 1.2.1.1 | B54: Benefiting Communities | C54: No. | D54: =SUM(MiniGrid!B53) -> 39 | E54: =SUM(MiniGrid!C53) -> 0
A55: 1.2.1.2 | B55: Isolated Mini Grid Approved | C55: No. | D55: =SUM(MiniGrid!B54) -> 0 | E55: =SUM(MiniGrid!C54) -> 0
A56: 1.2.1.3 | B56: Isolated Mini Grid Commissioned | C56: No. | D56: =SUM(MiniGrid!B55) -> 0 | E56: =SUM(MiniGrid!C55) -> 0
A57: 1.2.1.4 | B57: Isolated Mini-Grid Ongoing | C57: No. | D57: =SUM(MiniGrid!B56) -> 0 | E57: =SUM(MiniGrid!C56) -> 0
A58: 1.2.1.5 | B58: Population of beneficiaries | C58: No. | D58: =SUM(MiniGrid!B57) -> 0 | E58: =SUM(MiniGrid!C57) -> 0
A59: 1.2.1.6 | B59: Population of Female beneficiaries | C59: No. | D59: =SUM(MiniGrid!B58) -> 0 | E59: =SUM(MiniGrid!C58) -> 0
A60: 1.2.1.7 | B60: Population of Households | C60: No. | D60: =SUM(MiniGrid!B59) -> 0 | E60: =SUM(MiniGrid!C59) -> 0
A61: 1.2.1.8 | B61: Population of Female Headed Household beneficiaries | C61: No. | D61: =SUM(MiniGrid!B60) -> 0 | E61: =SUM(MiniGrid!C60) -> 0
A62: 1.2.1.9 | B62: Population of MSME beneficiaries | C62: No. | D62: =SUM(MiniGrid!B61) -> 0 | E62: =SUM(MiniGrid!C61) -> 0
A63: 1.2.1.10 | B63: Population of Female Managed MSME beneficiaries | C63: No. | D63: =SUM(MiniGrid!B62) -> 0 | E63: =SUM(MiniGrid!C62) -> 0
A64: 1.2.1.11 | B64: Population of New MSMEs enabled | C64: No. | D64: =SUM(MiniGrid!B63) -> 0 | E64: =SUM(MiniGrid!C63) -> 0
A65: 1.2.1.12 | B65: Population of Public Institutition beneficiary | C65: No. | D65: =SUM(MiniGrid!B64) -> 0 | E65: =SUM(MiniGrid!C64) -> 0
... A70: 1.2.1.19 | B70: Gasoline generator sets replaced | C70: No. | D70: =SUM(MiniGrid!B69) -> 40 | E70: =SUM(MiniGrid!C69) -> 0
A72: 1.2.2 | B72: Interconnected Mini Grid
A73: 1.2.2.1 | B73: Benefiting Communities | C73: No. | D73: =SUM(MiniGrid!B72) -> 40 | E73: =SUM(MiniGrid!C72) -> 0
A74: 1.2.2.2 | B74: Interconnected Mini Grid Approved | C74: No. | D74: =SUM(MiniGrid!B73) -> 0 | E74: =SUM(MiniGrid!C73) -> 0
A75: 1.2.2.3 | B75: Isolated Mini Grid Commissioned | C75: No. | D75: =SUM(MiniGrid!B74) -> 0 | E75: =SUM(MiniGrid!C74) -> 0
A76: 1.2.2.4 | B76: Interconnected Mini-Grid Ongoing | C76: No. | D76: =SUM(MiniGrid!B75) -> 0 | E76: =SUM(MiniGrid!C75) -> 0
A77: 1.2.2.5 | B77: Population of Households connected | C77: No. | D77: =SUM(MiniGrid!B76) -> 0 | E77: =SUM(MiniGrid!C76) -> 0
A78: 1.2.2.6 | B78: Population of Female Households connected | C78: No. | D78: =SUM(MiniGrid!B77) -> 0 | E78: =SUM(MiniGrid!C77) -> 0
A79: 1.2.2.7 | B79: Population of PUE and Economic Users connected | C79: No. | D79: =SUM(MiniGrid!B78) -> 0 | E79: =SUM(MiniGrid!C78) -> 0
A80: 1.2.2.8 | B80: Population of Female PUE and Economic Users | C80: No. | D80: =SUM(MiniGrid!B79) -> 0 | E80: =SUM(MiniGrid!C79) -> 0
A81: 1.2.2.9 | B81: Population of New PUE and Economic enabled | C81: No. | D81: =SUM(MiniGrid!B80) -> 0 | E81: =SUM(MiniGrid!C80) -> 0
A82: 1.2.2.10 | B82: Population of Public Institutition beneficiary | C82: KW | D82: =SUM(MiniGrid!B81) -> 0 | E82: =SUM(MiniGrid!C81) -> 0
A83: 1.2.2.11 | B83: Mini-Grid installed energy capacity | C83: No. | D83: =SUM(MiniGrid!B82) -> 0 | E83: =SUM(MiniGrid!C82) -> 0
A84: 1.2.2.12 | B84: Mini-Grid Energy generated | C84: No. | D84: =SUM(MiniGrid!B83) -> 0 | E84: =SUM(MiniGrid!C83) -> 0
... A87: 1.2.2.19 | B87: Gasoline generator sets replaced | C87: No. | D87: =SUM(MiniGrid!B86) -> 44 | E87: =SUM(MiniGrid!C86) -> 0
A89: 2 | B89: Component 2. Stand-alone Solar Systems for Households, MSMEs and Agribusinesses
A90: 2.1 | B90: Performance Based Grants for Standalone Solar Systems
A91: 2.1.1 | B91: Solar Home Systems deployed | C91: No. | D91: =SUM(StandAlone!C6) -> 23 | E91: =SUM(StandAlone!D6) -> 0
A92: 2.1.2 | B92: Installed Energy Capacity | C92: Kw | D92: =SUM(StandAlone!C7) -> 0 | E92: =SUM(StandAlone!D7) -> 0
A93: 2.1.3 | B93: Benefitting Households | C93: No. | D93: =SUM(StandAlone!C8) -> 0 | E93: =SUM(StandAlone!D8) -> 0
A94: 2.1.4 | B94: Benefiting Female Headed Households | C94: No. | D94: =SUM(StandAlone!C9) -> 0 | E94: =SUM(StandAlone!D9) -> 0
A95: 2.1.5 | B95: Benefiting MSMES | C95: No. | D95: =SUM(StandAlone!C10) -> 0 | E95: =SUM(StandAlone!D10) -> 0
A96: 2.1.6 | B96: Benefiting Female Owned MSMES | C96: No. | D96: =SUM(StandAlone!C11) -> 0 | E96: =SUM(StandAlone!D11) -> 0
A97: 2.1.7 | B97: Benefiting Agricultural Business | C97: No. | D97: =SUM(StandAlone!C12) -> 0 | E97: =SUM(StandAlone!D12) -> 0
A98: 2.1.8 | B98: Benefiting Female Owned Agricultural Business | C98: No. | D98: =SUM(StandAlone!C13) -> 0 | E98: =SUM(StandAlone!D13) -> 0
A99: 2.1.10 | B99: Private Sector Fund Mobilised | C99: USD | D99: =SUM(StandAlone!C15) -> 0 | E99: =SUM(StandAlone!D15) -> 0
A101: 2.2 | B101: Catalytic Grants
A102: 2.2.1 | B102: Poor/Displaced Communities Identified | C102: No. | D102: =SUM(StandAlone!C17) -> 25 | E102: =SUM(StandAlone!D17) -> 0
A103: 2.2.2 | B103: Poor/Displaced Communities Approved | C103: No. | D103: =SUM(StandAlone!C18) -> 0 | E103: =SUM(StandAlone!D18) -> 0
A104: 2.2.3 | B104: Solar Solution Approved | C104: No. | D104: =SUM(StandAlone!C19) -> 0 | E104: =SUM(StandAlone!D19) -> 0
A105: 2.2.4 | B105: Solar Solution Completed | C105: No. | D105: =SUM(StandAlone!C20) -> 0 | E105: =SUM(StandAlone!D20) -> 0
A106: 2.2.5 | B106: Solar Solution On-going | C106: No. | D106: =SUM(StandAlone!C21) -> 0 | E106: =SUM(StandAlone!D21) -> 0
A107: 2.2.6 | B107: Installed Energy Capacity | C107: Kw | D107: =SUM(StandAlone!C22) -> 0 | E107: =SUM(StandAlone!D22) -> 0
A108: 2.2.7 | B108: Population of Households | C108: No. | D108: =SUM(StandAlone!C23) -> 0 | E108: =SUM(StandAlone!D23) -> 0
A109: 2.2.8 | B109: Population of Female Headed Households | C109: No. | D109: =SUM(StandAlone!C24) -> 0 | E109: =SUM(StandAlone!D24) -> 0
A110: 2.2.9 | B110: Population of PUE and Economic Users | C110: No. | D110: =SUM(StandAlone!C25) -> 0 | E110: =SUM(StandAlone!D25) -> 0
A111: 2.2.13 | B111: Population of Female PUE and Economic Users | C111: No. | D111: =SUM(StandAlone!C26) -> 0 | E111: =SUM(StandAlone!D26) -> 0
B112: Gasoline generator sets replaced | C112: No. | D112: =SUM(StandAlone!C27) -> 26 | E112: =SUM(StandAlone!D27) -> 0
A114: 3 | B114: TECHNICAL ASSISTANCE
A115: 3.1 | B115: Financial Management
A116: 3.1.1 | B116: Quarterly IFRs Submitted | C116: No | D116: =SUM(FM!E5) -> 0 | E116: =SUM(FM!F5) -> 0
A117: 3.1.2 | B117: % Budget Execution (Actual vs. Planned) | C117: % | D117: =SUM(FM!E6) -> 0 | E117: =SUM(FM!F6) -> 0
A118: 3.1.3 | B118: External Audit produced | C118: No | D118: =SUM(FM!E7) -> 0 | E118: =SUM(FM!F7) -> 0
A119: 3.1.4 | B119: Amount Replenished | C119: USD | D119: =SUM(FM!E8) -> 0 | E119: =SUM(FM!F8) -> 0
...

Sheet FM
B1: DARES PROJECT: FINANCIAL MANAGEMENT PERFORMANCE TEMPLATE
B3: Reporting Period______________________________________
B4: Indicators | E4: Current Quarter | F4: To-date
B5: Quarterly IFRs Submitted
B6: % Budget Execution (Actual vs. Planned)
B7: External Audit produced
B8: Amount Replenished
B9: Amount Converted
B10: Government Contribution
B12: FINANCIAL STATUS
A13: S/N | B13: Component | D13: IDA Allocation | E13: IDA Alllocation | F13: Previous Cumulative Disbursement | G13: Current Quarter Disbursement | H13: Disbursement To-date
A14: 1 | B14: Mini Grids
A15: 1.1 | B15: Minimum Subsidy Tender | C15: Isolated Mini Grids | E15: 95000000
C16: Interconnected Mini Grids | E16: 100000000
C17: Solar Roof Top | E17: 20000000
A18: 1.2 | B18: Performance Based Grants | C18: Isolated Mini Grids | E18: 168000000
C19: Interconnected Mini Grids | E19: 27000000
A20: Total Component 1 | E20: 410000000
A21: 2 | B21: Standalone Solar
A22: 2.1 | B22: Performance Based Grants | C22: SAS Basic Electrification | E22: 230000000
C23: SAS PUE | E23: 50000000
A24: 2.2 | B24: Catalytic Grants | E24: 20000000
A25: Total Component 2 | E25: 300000000
A26: 3 | B26: Technical Assistance
A27: 3.1 | B27: Institutional strengthening | E27: 10000000
A28: 3.2 | B28: Ecosystem building | E28: 20000000
A29: 3.3 | B29: Engagement with States | E29: 10000000
A30: Total Component 3 | E30: 40000000
B31: TOTAL DARES | E31: 750000000
B34: Summary and Next Steps
B35: Key Achievements | D35: Challenges | F35: Way Forward | H35: Actions Planned for Next Period

Sheet Procurement
B2: PROCUREMENT
B3: Reporting Period______________________________________
B4: Category | D4: Measure | E4: Goods | G4: Works | I4: Non-Consulting | K4: Consultancy
E5: Current Quarter | F5: To date | G5: Current Quarter | H5: To date | I5: Current Quarter | J5: To date | K5: Current Quarter | L5: To date
B6: EOI | D6: No
B7: RFP | D7: No
B8: Awarded | D8: No
B9: Contract sum | D9: Naira
B10: Contract Completed | D10: No
B11: Contract On-going | D11: No
B12: *Contract Delayed | D12: No
B15: Summary and Next Steps
B16: Key Achievements | D16: Challenges | G16: Way Forward | J16: Actions Planned for Next Period

Sheet Intergovernmental
B2: INTERGOVERNMENTAL SERVICES
B3: Reporting Period______________________________________
B5: 1. Stakeholder Engagement
B6: Type | C6: Stakeholder Identity | D6: Level (Federal/State) | E6: Purpose of Engagement
B12: 2. MOUs and Agreements
B13: MOU Type | C13: Key Commitments | E13: Status (Signed/ Pending/Under Review)
B20: 3. Issues Identified
B21: Issue Description | C21: Stakeholders Involved | E21: Impact on Project | H21: Action Taken/Recommendation
B26: 4. Planned Activities for Next Reporting Period
B27: Activity | C27: Objective | F27: Target State(s) | H27: Expected Outcome
B65: Key Achievements | C65: Challenges | D65: Way Forward | E65: Actions Planned for Next Period

Sheet Environment
B2: ENVIRONMENTAL SAFEGUARDS
B4: Period: ________________________________
B5: Indicators | C5: Current Quarter | D5: To-date
B6: Occupational Health Safety cases reported | C6: 1 | D6: 2
B7: Sites with undisposed electronic waste, heaps of debris or piles after construction
B8: Sites with Erosion/Flooding issues
B9: Site with Ground/Surface Water pollution
B10: Site with abandoned borrow pits | C10: 3 | D10: 4
B12: Summary and Next Steps
B13: Key Achievements | C13: Challenges | E13: Way Forward | H13: Actions Planned for Next Period

Sheet HR
B2: HUMAN RESOURCES & ADMINISTRATION
B4: Reporting Period______________________________________
B5: Indicators | C5: Current Quarter | D5: To-date
B6: No. of Staff
B7: % of Female Staff
B8: Staff trained
B9: Meetings held and reported
B11: Summary and Next Steps
B12: Key Achievements | C12: Challenges | E12: Way Forward | H12: Actions Planned for Next Period

Sheet Social
B2: SOCIAL SAFEGUARDS PERFORMANCE REPORT
B3: Reporting Period: ________________________________
B4: Indicators | C4: Current Quarter | D4: To-date
B5: Volountary Land Donation Protocol cases reported
B6: % of Volountary Land Donation Protocol cases resolved
B7: Exclusion and discrimination cases reported
B8: % of Exclusion and discrimination cases resolved
B9: GBV/SH/SEA cases reported
B10: Labour Management cases reported
B11: % of Labour Management cases resolved
B14: Summary and Next Steps
B15: Key Achievements | C15: Challenges | E15: Way Forward | H15: Actions Planned for Next Period

Sheet Communication
B2: COMMUNICATION
B4: Reporting Period
B5: Indicators | C5: Current Quarter | D5: To-date
B6: Public awareness campaigns conducted
B7: Media engagement conducted
B8: Stakeholder engagement events held
B9: Website/portal update frequency
B10: Social media posted
B11: Online inquiries received
B12: Online inquiries addressed
B13: Internal knowledge sharing sessions held
B14: Publications produced and distributed
B15: Jingles and media programmes aired
B17: Summary and Next Steps
B18: Key Achievements | C18: Challenges | E18: Way Forward | H18: Actions Planned for Next Period

Sheet IT
B2: INFORMATION AND TECHNOLOGY
B4: Reporting Period: ____________________________________________
B6: Indicators | C6: Current Quarter | D6: To-date
B7: Remote Monitoring, Data Centre, and Project Feedback System
B8: Number of data sources connected to the DARES data center
B9: Sites minigrid sites connected to the DARES Data center
B10: Total Solar Homes System connected to data center
B11: Total number of external stakeholder visiting the Data center
B13: Smart Office Solutions, Website, and Gmail
B14: Staff onboarded onto Smart Office platforms
B15: Total no of reports submittted
B16: Total no of reports approved
B17: Total number of visits to the office
B18: Total meeting schedules
B19: Total meeting attended
... B38: Summary and Next Steps
B39: Key Achievements | C39: Challenges | E39: Way Forward | H39: Actions Planned for Next Period
